steinernet/__init__.py
steinernet/random_walk_subgraph.py
steinernet/steiner.py
steinernet/wilcoxon_analysis.py
steinernet-0.2.0.dist-info/licenses/LICENSE-2.0.txt
steinernet-0.2.0.dist-info/METADATA
steinernet-0.2.0.dist-info/WHEEL
steinernet-0.2.0.dist-info/entry_points.txt
steinernet-0.2.0.dist-info/top_level.txt
steinernet-0.2.0.dist-info/RECORD
