Metadata-Version: 2.4
Name: steinernet
Version: 0.2.0
Summary: A SteinerTree library implementing several huristic and exact steiner methods.
Home-page: https://github.com/afshinsadeghi/steinernetpy
Author: Afshin Sadeghi
Author-email: Afshin Sadeghi <sadeghi.afshin@gmail.com>
License-Expression: Apache-2.0
Requires-Python: >=3.7
License-File: LICENSE-2.0.txt
Requires-Dist: networkx>=2.0
Dynamic: author
Dynamic: home-page
Dynamic: license-file
Dynamic: requires-python
